localizesh_sdk/__init__.py
localizesh_sdk/generators.py
localizesh_sdk/mappers.py
localizesh_sdk/types.py
localizesh_sdk/protos/localize/document_pb2.py
localizesh_sdk/protos/localize/processor_pb2.py
localizesh_sdk/protos/localize/segment_pb2.py
localizesh_sdk-0.1.4.dist-info/METADATA
localizesh_sdk-0.1.4.dist-info/WHEEL
localizesh_sdk-0.1.4.dist-info/top_level.txt
localizesh_sdk-0.1.4.dist-info/RECORD
